espresso/__init__.py
espresso/atomic_configs.py
espresso/espresso.py
espresso/nebespresso.py
espresso/siteconfig.py
espresso/utils.py
espresso/vibespresso.py
espresso/worldstub.py
aseqe-0.3.4.dist-info/AUTHORS
aseqe-0.3.4.dist-info/COPYING
aseqe-0.3.4.dist-info/METADATA
aseqe-0.3.4.dist-info/WHEEL
aseqe-0.3.4.dist-info/top_level.txt
aseqe-0.3.4.dist-info/RECORD
