Metadata-Version: 2.1
Name: aseqe
Version: 0.3.4
Summary: Python API for the Quantum Espresso software
Home-page: https://github.com/lmmentel/ase-espresso
Author: Lukasz Mentel
Author-email: lmmentel@gmail.com
License: GPLv3
Keywords: chemistry physics quantum mechanics solid state
Platform: UNKNOWN
Classifier: Development Status :: 3 - Alpha
Classifier: Environment :: Console
Classifier: Intended Audience :: Science/Research
Classifier: License :: OSI Approved :: GNU General Public License v3 (GPLv3)
Classifier: Natural Language :: English
Classifier: Programming Language :: Python
Classifier: Programming Language :: Python :: 2
Classifier: Programming Language :: Python :: 3
Classifier: Topic :: Scientific/Engineering :: Chemistry
Classifier: Topic :: Scientific/Engineering :: Physics
Requires-Dist: ase
Requires-Dist: future
Requires-Dist: numpy
Requires-Dist: path.py
Requires-Dist: pexpect
Requires-Dist: python-hostlist
Requires-Dist: six
